fcw_client_python/__init__.py
fcw_client_python/client_python.py
fcw_client_python/client_python_middleware.py
fcw_client_python/client_python_simple.py
fcw_client/__init__.py
fcw_client/client_common.py
fcw_client-0.12.1.dist-info/METADATA
fcw_client-0.12.1.dist-info/WHEEL
fcw_client-0.12.1.dist-info/entry_points.txt
fcw_client-0.12.1.dist-info/RECORD
