Metadata-Version: 2.1
Name: fcw-client
Version: 0.12.1
Summary: Early collision warning Network Application for Transportation use case - client part
Home-page: https://github.com/5G-ERA/CollisionWarningService
Author: Petr Kleparnik
Author-email: p.kleparnik@cognitechna.cz
Requires-Python: >=3.8
Classifier: Programming Language :: Python :: 3
Classifier: Programming Language :: Python :: 3.8
Classifier: Programming Language :: Python :: 3.9
Classifier: Programming Language :: Python :: 3.10
Classifier: Programming Language :: Python :: 3.11
Classifier: Programming Language :: Python :: 3.12
Requires-Dist: era-5g-client (>=0.11.0,<0.12.0)
Requires-Dist: era-5g-interface (>=0.10.0,<0.11.0)
Requires-Dist: fcw-core-utils (>=0.12.1,<0.13.0)
Requires-Dist: opencv-python (>=4.8)
Requires-Dist: pyyaml (>=6.0.1)
Project-URL: Repository, https://github.com/5G-ERA/CollisionWarningService
